{
    "fluentMethods": true,
    "relationships": [
        {
            "relationshipType": "one-to-one",
            "relationshipName": "contentType",
            "otherEntityName": "contentType",
            "otherEntityField": "name",
            "ownerSide": true,
            "otherEntityRelationshipName": "material"
        }
    ],
    "fields": [
        {
            "fieldName": "title",
            "fieldType": "String"
        },
        {
            "fieldName": "description",
            "fieldType": "String"
        },
        {
            "fieldName": "duration",
            "fieldType": "Long"
        },
        {
            "fieldName": "companyId",
            "fieldType": "Long"
        },
        {
            "fieldName": "cdn",
            "fieldType": "String"
        }
    ],
    "changelogDate": "20170916094639",
    "entityTableName": "material",
    "dto": "no",
    "pagination": "pagination",
    "service": "no"
}